[[{"vacancy_name": "\n              \u0421\u0438\u0441\u0442\u0435\u043c\u043d\u044b\u0439 \u0430\u0434\u043c\u0438\u043d\u0438\u0441\u0442\u0440\u0430\u0442\u043e\u0440\n            ", "vacancy_link": "https://nsk.rabota.ru//vacancy/47127997/?search_id=1673541404142yon2sxp63p", "salary_min": "80\u00a0000\u00a0\u2014", "salary_max": "200\u00a0000", "salary_currency": "\u0440\u0443\u0431.", "vacancy_employee": "\n              Jobers\n            ", "resource": "rabota_ru"}, {"vacancy_name": "\n              \u0421\u0438\u0441\u0442\u0435\u043c\u043d\u044b\u0439 \u0430\u0434\u043c\u0438\u043d\u0438\u0441\u0442\u0440\u0430\u0442\u043e\u0440\n            ", "vacancy_link": "https://nsk.rabota.ru//vacancy/47127997/?search_id=1673541404142yon2sxp63p", "salary_min": "80\u00a0000\u00a0\u2014", "salary_max": "200\u00a0000", "salary_currency": "\u0440\u0443\u0431.", "vacancy_employee": "\n              Jobers\n            ", "resource": "rabota_ru"}, {"vacancy_name": "\n              \u0421\u0438\u0441\u0442\u0435\u043c\u043d\u044b\u0439 \u0430\u0434\u043c\u0438\u043d\u0438\u0441\u0442\u0440\u0430\u0442\u043e\u0440\n            ", "vacancy_link": "https://nsk.rabota.ru//vacancy/47127997/?search_id=1673541404142yon2sxp63p", "salary_min": "80\u00a0000\u00a0\u2014", "salary_max": "200\u00a0000", "salary_currency": "\u0440\u0443\u0431.", "vacancy_employee": "\n              Jobers\n            ", "resource": "rabota_ru"}], [{"vacancy_name": "\n              \u0414\u0440\u043e\u0431\u0438\u043b\u044c\u0449\u0438\u043a\n            ", "vacancy_link": "https://nsk.rabota.ru//vacancy/46750588/?search_id=1673541404142yon2sxp63p", "salary_min": "23\u00a0000\u00a0\u2014", "salary_max": "33\u00a0000", "salary_currency": "\u0440\u0443\u0431.", "vacancy_employee": "\n              \u041e\u041e\u041e  \"\u0424\u041e\u041f\u041e\u0421\"\n            ", "resource": "rabota_ru"}, {"vacancy_name": "\n              \u0414\u0440\u043e\u0431\u0438\u043b\u044c\u0449\u0438\u043a\n            ", "vacancy_link": "https://nsk.rabota.ru//vacancy/46750588/?search_id=1673541404142yon2sxp63p", "salary_min": "23\u00a0000\u00a0\u2014", "salary_max": "33\u00a0000", "salary_currency": "\u0440\u0443\u0431.", "vacancy_employee": "\n              \u041e\u041e\u041e  \"\u0424\u041e\u041f\u041e\u0421\"\n            ", "resource": "rabota_ru"}, {"vacancy_name": "\n              \u0414\u0440\u043e\u0431\u0438\u043b\u044c\u0449\u0438\u043a\n            ", "vacancy_link": "https://nsk.rabota.ru//vacancy/46750588/?search_id=1673541404142yon2sxp63p", "salary_min": "23\u00a0000\u00a0\u2014", "salary_max": "33\u00a0000", "salary_currency": "\u0440\u0443\u0431.", "vacancy_employee": "\n              \u041e\u041e\u041e  \"\u0424\u041e\u041f\u041e\u0421\"\n            ", "resource": "rabota_ru"}], [{"vacancy_name": "\n              \u0421\u043e\u0440\u0442\u0438\u0440\u043e\u0432\u0449\u0438\u043a/\u0446\u0430, \u0443\u043a\u043b\u0430\u0434\u0447\u0438\u043a/\u0446\u0430-\u0443\u043f\u0430\u043a\u043e\u0432\u0449\u0438\u043a/\u0446\u0430\n            ", "vacancy_link": "https://nsk.rabota.ru//vacancy/46760112/?search_id=1673541404142yon2sxp63p", "salary_min": "30\u00a0000\u00a0\u2014", "salary_max": "70\u00a0000", "salary_currency": "\u0440\u0443\u0431.", "vacancy_employee": "\n              \u041e\u041e\u041e  \"\u0424\u041e\u041f\u041e\u0421\"\n            ", "resource": "rabota_ru"}, {"vacancy_name": "\n              \u0421\u043e\u0440\u0442\u0438\u0440\u043e\u0432\u0449\u0438\u043a/\u0446\u0430, \u0443\u043a\u043b\u0430\u0434\u0447\u0438\u043a/\u0446\u0430-\u0443\u043f\u0430\u043a\u043e\u0432\u0449\u0438\u043a/\u0446\u0430\n            ", "vacancy_link": "https://nsk.rabota.ru//vacancy/46760112/?search_id=1673541404142yon2sxp63p", "salary_min": "30\u00a0000\u00a0\u2014", "salary_max": "70\u00a0000", "salary_currency": "\u0440\u0443\u0431.", "vacancy_employee": "\n              \u041e\u041e\u041e  \"\u0424\u041e\u041f\u041e\u0421\"\n            ", "resource": "rabota_ru"}, {"vacancy_name": "\n              \u0421\u043e\u0440\u0442\u0438\u0440\u043e\u0432\u0449\u0438\u043a/\u0446\u0430, \u0443\u043a\u043b\u0430\u0434\u0447\u0438\u043a/\u0446\u0430-\u0443\u043f\u0430\u043a\u043e\u0432\u0449\u0438\u043a/\u0446\u0430\n            ", "vacancy_link": "https://nsk.rabota.ru//vacancy/46760112/?search_id=1673541404142yon2sxp63p", "salary_min": "30\u00a0000\u00a0\u2014", "salary_max": "70\u00a0000", "salary_currency": "\u0440\u0443\u0431.", "vacancy_employee": "\n              \u041e\u041e\u041e  \"\u0424\u041e\u041f\u041e\u0421\"\n            ", "resource": "rabota_ru"}], [{"vacancy_name": "\n              \u0414\u0435\u0436\u0443\u0440\u043d\u044b\u0439 \u043d\u0430\u043b\u0430\u0434\u0447\u0438\u043a\n            ", "vacancy_link": "https://nsk.rabota.ru//vacancy/45646494/?search_id=1673541404142yon2sxp63p", "salary_min": "35\u00a0000\u00a0\u2014", "salary_max": "45\u00a0000", "salary_currency": "\u0440\u0443\u0431.", "vacancy_employee": "\n              \u041e\u041e\u041e \"\u0421\u0438\u0431-\u041f\u0440\u0435\u0441\u0441\"\n            ", "resource": "rabota_ru"}, {"vacancy_name": "\n              \u0414\u0435\u0436\u0443\u0440\u043d\u044b\u0439 \u043d\u0430\u043b\u0430\u0434\u0447\u0438\u043a\n            ", "vacancy_link": "https://nsk.rabota.ru//vacancy/45646494/?search_id=1673541404142yon2sxp63p", "salary_min": "35\u00a0000\u00a0\u2014", "salary_max": "45\u00a0000", "salary_currency": "\u0440\u0443\u0431.", "vacancy_employee": "\n              \u041e\u041e\u041e \"\u0421\u0438\u0431-\u041f\u0440\u0435\u0441\u0441\"\n            ", "resource": "rabota_ru"}, {"vacancy_name": "\n              \u0414\u0435\u0436\u0443\u0440\u043d\u044b\u0439 \u043d\u0430\u043b\u0430\u0434\u0447\u0438\u043a\n            ", "vacancy_link": "https://nsk.rabota.ru//vacancy/45646494/?search_id=1673541404142yon2sxp63p", "salary_min": "35\u00a0000\u00a0\u2014", "salary_max": "45\u00a0000", "salary_currency": "\u0440\u0443\u0431.", "vacancy_employee": "\n              \u041e\u041e\u041e \"\u0421\u0438\u0431-\u041f\u0440\u0435\u0441\u0441\"\n            ", "resource": "rabota_ru"}], [{"vacancy_name": "\n              \u041d\u0430\u043b\u0430\u0434\u0447\u0438\u043a \u043e\u0431\u043e\u0440\u0443\u0434\u043e\u0432\u0430\u043d\u0438\u044f\n            ", "vacancy_link": "https://nsk.rabota.ru//vacancy/45646492/?search_id=1673541404142yon2sxp63p", "salary_min": "40\u00a0000\u00a0\u2014", "salary_max": "50\u00a0000", "salary_currency": "\u0440\u0443\u0431.", "vacancy_employee": "\n              \u041e\u041e\u041e \"\u0421\u0438\u0431-\u041f\u0440\u0435\u0441\u0441\"\n            ", "resource": "rabota_ru"}, {"vacancy_name": "\n              \u041d\u0430\u043b\u0430\u0434\u0447\u0438\u043a \u043e\u0431\u043e\u0440\u0443\u0434\u043e\u0432\u0430\u043d\u0438\u044f\n            ", "vacancy_link": "https://nsk.rabota.ru//vacancy/45646492/?search_id=1673541404142yon2sxp63p", "salary_min": "40\u00a0000\u00a0\u2014", "salary_max": "50\u00a0000", "salary_currency": "\u0440\u0443\u0431.", "vacancy_employee": "\n              \u041e\u041e\u041e \"\u0421\u0438\u0431-\u041f\u0440\u0435\u0441\u0441\"\n            ", "resource": "rabota_ru"}, {"vacancy_name": "\n              \u041d\u0430\u043b\u0430\u0434\u0447\u0438\u043a \u043e\u0431\u043e\u0440\u0443\u0434\u043e\u0432\u0430\u043d\u0438\u044f\n            ", "vacancy_link": "https://nsk.rabota.ru//vacancy/45646492/?search_id=1673541404142yon2sxp63p", "salary_min": "40\u00a0000\u00a0\u2014", "salary_max": "50\u00a0000", "salary_currency": "\u0440\u0443\u0431.", "vacancy_employee": "\n              \u041e\u041e\u041e \"\u0421\u0438\u0431-\u041f\u0440\u0435\u0441\u0441\"\n            ", "resource": "rabota_ru"}], [{"vacancy_name": "\n              \u041e\u043f\u0435\u0440\u0430\u0442\u043e\u0440 \u0441\u0442\u0430\u043d\u043a\u0430 \u0441 \u0427\u041f\u0423\n            ", "vacancy_link": "https://nsk.rabota.ru//vacancy/45646489/?search_id=1673541404142yon2sxp63p", "salary_min": "30\u00a0000\u00a0\u2014", "salary_max": "50\u00a0000", "salary_currency": "\u0440\u0443\u0431.", "vacancy_employee": "\n              \u041e\u041e\u041e \"\u0421\u0438\u0431-\u041f\u0440\u0435\u0441\u0441\"\n            ", "resource": "rabota_ru"}, {"vacancy_name": "\n              \u041e\u043f\u0435\u0440\u0430\u0442\u043e\u0440 \u0441\u0442\u0430\u043d\u043a\u0430 \u0441 \u0427\u041f\u0423\n            ", "vacancy_link": "https://nsk.rabota.ru//vacancy/45646489/?search_id=1673541404142yon2sxp63p", "salary_min": "30\u00a0000\u00a0\u2014", "salary_max": "50\u00a0000", "salary_currency": "\u0440\u0443\u0431.", "vacancy_employee": "\n              \u041e\u041e\u041e \"\u0421\u0438\u0431-\u041f\u0440\u0435\u0441\u0441\"\n            ", "resource": "rabota_ru"}, {"vacancy_name": "\n              \u041e\u043f\u0435\u0440\u0430\u0442\u043e\u0440 \u0441\u0442\u0430\u043d\u043a\u0430 \u0441 \u0427\u041f\u0423\n            ", "vacancy_link": "https://nsk.rabota.ru//vacancy/45646489/?search_id=1673541404142yon2sxp63p", "salary_min": "30\u00a0000\u00a0\u2014", "salary_max": "50\u00a0000", "salary_currency": "\u0440\u0443\u0431.", "vacancy_employee": "\n              \u041e\u041e\u041e \"\u0421\u0438\u0431-\u041f\u0440\u0435\u0441\u0441\"\n            ", "resource": "rabota_ru"}], [{"vacancy_name": "\n              \u041f\u0440\u043e\u0434\u0430\u0432\u0435\u0446\n            ", "vacancy_link": "https://nsk.rabota.ru//vacancy/43780150/?search_id=1673541404142yon2sxp63p", "salary_min": "28\u00a0000\u00a0\u2014", "salary_max": "35\u00a0000", "salary_currency": "\u0440\u0443\u0431.", "vacancy_employee": "\n              \u0418\u043d\u0434\u0438\u0432\u0438\u0434\u0443\u0430\u043b\u044c\u043d\u044b\u0439 \u043f\u0440\u0435\u0434\u043f\u0440\u0438\u043d\u0438\u043c\u0430\u0442\u0435\u043b\u044c \u041c\u043e\u0437\u0430\u043b\u044e\u043a \u041e\u043a\u0441\u0430\u043d\u0430 \u0412\u0438\u043a\u0442\u043e\u0440\u043e\u0432\u043d\u0430\n            ", "resource": "rabota_ru"}, {"vacancy_name": "\n              \u041f\u0440\u043e\u0434\u0430\u0432\u0435\u0446\n            ", "vacancy_link": "https://nsk.rabota.ru//vacancy/43780150/?search_id=1673541404142yon2sxp63p", "salary_min": "28\u00a0000\u00a0\u2014", "salary_max": "35\u00a0000", "salary_currency": "\u0440\u0443\u0431.", "vacancy_employee": "\n              \u0418\u043d\u0434\u0438\u0432\u0438\u0434\u0443\u0430\u043b\u044c\u043d\u044b\u0439 \u043f\u0440\u0435\u0434\u043f\u0440\u0438\u043d\u0438\u043c\u0430\u0442\u0435\u043b\u044c \u041c\u043e\u0437\u0430\u043b\u044e\u043a \u041e\u043a\u0441\u0430\u043d\u0430 \u0412\u0438\u043a\u0442\u043e\u0440\u043e\u0432\u043d\u0430\n            ", "resource": "rabota_ru"}, {"vacancy_name": "\n              \u041f\u0440\u043e\u0434\u0430\u0432\u0435\u0446\n            ", "vacancy_link": "https://nsk.rabota.ru//vacancy/43780150/?search_id=1673541404142yon2sxp63p", "salary_min": "28\u00a0000\u00a0\u2014", "salary_max": "35\u00a0000", "salary_currency": "\u0440\u0443\u0431.", "vacancy_employee": "\n              \u0418\u043d\u0434\u0438\u0432\u0438\u0434\u0443\u0430\u043b\u044c\u043d\u044b\u0439 \u043f\u0440\u0435\u0434\u043f\u0440\u0438\u043d\u0438\u043c\u0430\u0442\u0435\u043b\u044c \u041c\u043e\u0437\u0430\u043b\u044e\u043a \u041e\u043a\u0441\u0430\u043d\u0430 \u0412\u0438\u043a\u0442\u043e\u0440\u043e\u0432\u043d\u0430\n            ", "resource": "rabota_ru"}]]